tsol.py
tsol-0.1.dist-info/DESCRIPTION.rst
tsol-0.1.dist-info/METADATA
tsol-0.1.dist-info/RECORD
tsol-0.1.dist-info/WHEEL
tsol-0.1.dist-info/entry_points.txt
tsol-0.1.dist-info/metadata.json
tsol-0.1.dist-info/top_level.txt
