Metadata-Version: 2.0
Name: tsol
Version: 0.1
Summary: Templated Solidity for smart contracts.
Home-page: https://github.com/lamden/tsol
Author: Lamden GmbH
Author-email: team@lamden.io
License: UNKNOWN
Download-URL: https://github.com/lamden/tsol/archive/0.1.tar.gz
Keywords: ethereum,solidity,cryptocurrency
Platform: UNKNOWN
Requires-Dist: Jinja2
Requires-Dist: click
Requires-Dist: py-solc
Requires-Dist: requests
